ExponEncryption/__init__.py
ExponEncryption/encryption_V2.py
exponencryption-0.6.0.dist-info/licenses/LICENSE
exponencryption-0.6.0.dist-info/METADATA
exponencryption-0.6.0.dist-info/WHEEL
exponencryption-0.6.0.dist-info/top_level.txt
exponencryption-0.6.0.dist-info/RECORD
